diagv/__init__.py
diagv/generators.py
diagv/misc.py
diagv/optimization.py
diagv/py.typed
diagv/typing_utils.py
diagv/visualization.py
diagv-0.2.dist-info/METADATA
diagv-0.2.dist-info/WHEEL
diagv-0.2.dist-info/top_level.txt
diagv-0.2.dist-info/RECORD
