Metadata-Version: 2.1
Name: diagv
Version: 0.2
Summary: Diagonal Directed Graph Visualization
Home-page: https://github.com/apljungquist/diagv
Author: AP Ljungquist
Author-email: ap@ljungquist.eu
License: UNKNOWN
Platform: UNKNOWN
Requires-Python: >=3.9
Requires-Dist: more-itertools
Requires-Dist: networkx
Requires-Dist: numpy
Provides-Extra: examples
Requires-Dist: fire ; extra == 'examples'
Requires-Dist: matplotlib ; extra == 'examples'
Requires-Dist: scipy ; extra == 'examples'
